{
  "usuarios": [
    {
      "url": "http://localhost:4000/usuarios/",
      "nombre": "John David",
      "apellido": "Betancur Román",
      "correo": "david@gmail.com",
      "id": 1
    },
    {
      "url": "http://localhost:4000/usuarios/",
      "nombre": "Hernani Gonzalez",
      "apellido": "Gonzalez",
      "correo": "chernani@gmail.com",
      "id": 2
    },
    {
      "url": "http://localhost:4000/usuarios/",
      "nombre": "",
      "apellido": "",
      "correo": "chernani@gmail.com",
      "id": 3
    }
  ]
}